MANIFEST.in
README.md
setup.cfg
setup.py
versioneer.py
torch_gauge/__init__.py
torch_gauge/_version.py
torch_gauge/geometric.py
torch_gauge/nn.py
torch_gauge/verlet_list.py
torch_gauge.egg-info/PKG-INFO
torch_gauge.egg-info/SOURCES.txt
torch_gauge.egg-info/dependency_links.txt
torch_gauge.egg-info/requires.txt
torch_gauge.egg-info/top_level.txt
torch_gauge/models/descriptors.py
torch_gauge/models/gnn.py
torch_gauge/o3/__init__.py
torch_gauge/o3/clebsch_gordan.py
torch_gauge/o3/functional.py
torch_gauge/o3/rsh.py
torch_gauge/o3/spherical.py
torch_gauge/o3/wigner.py
torch_gauge/tests/test_cg_parity_o3.py
torch_gauge/tests/test_clebsch_gordan.py
torch_gauge/tests/test_nn_layers.py
torch_gauge/tests/test_nn_training.py
torch_gauge/tests/test_rshs.py
torch_gauge/tests/test_spherical_tensor.py
torch_gauge/tests/test_verlet_list.py