Metadata-Version: 2.1
Name: torch-gauge
Version: 0.1.3.3
Summary: A light-weight PyTorch extension for gauge-equivariant geometric learning
Home-page: UNKNOWN
Author: Zhuoran Qiao
Author-email: zqiao@caltech.edu
License: UNKNOWN
Platform: UNKNOWN
Requires-Python: >=3.7
